html_document_generator/__init__.py
html_document_generator/html_document_generator.py
html_document_generator/test.py
HTMLDocumentGenerator-1.0.3.dist-info/LICENSE
HTMLDocumentGenerator-1.0.3.dist-info/METADATA
HTMLDocumentGenerator-1.0.3.dist-info/WHEEL
HTMLDocumentGenerator-1.0.3.dist-info/top_level.txt
HTMLDocumentGenerator-1.0.3.dist-info/RECORD
