Metadata-Version: 2.1
Name: HTMLDocumentGenerator
Version: 1.0.3
Summary: The HTMLDocumentGenerator is a Python class that allows you to easily generate HTML documents with customizable tags and content. It provides a simple and intuitive way to create HTML documents for websites or other applications.
Author: Ouedraogo Somkiéta Rahim Alex
Author-email: Ouedraogo Somkieta Rahim Alex <s.r.a.ouedraogo@gmail.com>
License: MIT
Project-URL: Homepage, https://github.com/somkietacode/HTMLDocumentGenerator
Project-URL: Bug Tracker, https://github.com/somkietacode/HTMLDocumentGenerator/issues
Platform: any
Classifier: Programming Language :: Python :: 3
Classifier: License :: OSI Approved :: MIT License
Classifier: Operating System :: OS Independent
Requires-Python: >=3.6
License-File: LICENSE
Requires-Dist: importlib-metadata ; python_version < "3.6"
Requires-Dist: importlib-metadata ; python_version == "3.6"
